{
  "key": "plugin_content_manager_configuration_content_types::api::post.post",
  "value": {
    "uid": "api::post.post",
    "settings": {
      "bulkable": true,
      "filterable": true,
      "searchable": true,
      "pageSize": 100,
      "mainField": "title",
      "defaultSortBy": "title",
      "defaultSortOrder": "ASC"
    },
    "metadatas": {
      "id": {
        "edit": {},
        "list": {
          "label": "Id",
          "searchable": true,
          "sortable": true
        }
      },
      "type": {
        "edit": {
          "label": "Type",
          "description": "",
          "placeholder": "",
          "visible": true,
          "editable": true
        },
        "list": {
          "label": "Type",
          "searchable": true,
          "sortable": true
        }
      },
      "date": {
        "edit": {
          "label": "Date",
          "description": "",
          "placeholder": "",
          "visible": true,
          "editable": true
        },
        "list": {
          "label": "Date",
          "searchable": true,
          "sortable": true
        }
      },
      "legacyId": {
        "edit": {
          "label": "LegacyId",
          "description": "",
          "placeholder": "",
          "visible": true,
          "editable": true
        },
        "list": {
          "label": "LegacyId",
          "searchable": true,
          "sortable": true
        }
      },
      "title": {
        "edit": {
          "label": "Title",
          "description": "",
          "placeholder": "",
          "visible": true,
          "editable": true
        },
        "list": {
          "label": "Title",
          "searchable": true,
          "sortable": true
        }
      },
      "content": {
        "edit": {
          "label": "Content",
          "description": "",
          "placeholder": "",
          "visible": true,
          "editable": true
        },
        "list": {
          "label": "Content",
          "searchable": false,
          "sortable": false
        }
      },
      "excerpt": {
        "edit": {
          "label": "Excerpt",
          "description": "",
          "placeholder": "",
          "visible": true,
          "editable": true
        },
        "list": {
          "label": "Excerpt",
          "searchable": true,
          "sortable": true
        }
      },
      "slug": {
        "edit": {
          "label": "Slug",
          "description": "",
          "placeholder": "",
          "visible": true,
          "editable": true
        },
        "list": {
          "label": "Slug",
          "searchable": true,
          "sortable": true
        }
      },
      "tags": {
        "edit": {
          "label": "tags",
          "description": "",
          "placeholder": "",
          "visible": true,
          "editable": true,
          "mainField": "name"
        },
        "list": {
          "label": "tags",
          "searchable": false,
          "sortable": false
        }
      },
      "seo": {
        "edit": {
          "label": "seo",
          "description": "",
          "placeholder": "",
          "visible": true,
          "editable": true
        },
        "list": {
          "label": "seo",
          "searchable": false,
          "sortable": false
        }
      },
      "featuredImage": {
        "edit": {
          "label": "FeaturedImage",
          "description": "",
          "placeholder": "",
          "visible": true,
          "editable": true
        },
        "list": {
          "label": "FeaturedImage",
          "searchable": false,
          "sortable": false
        }
      },
      "gallery": {
        "edit": {
          "label": "gallery",
          "description": "",
          "placeholder": "",
          "visible": true,
          "editable": true
        },
        "list": {
          "label": "gallery",
          "searchable": false,
          "sortable": false
        }
      },
      "legacyFeaturedImage": {
        "edit": {
          "label": "legacyFeaturedImage",
          "description": "",
          "placeholder": "",
          "visible": true,
          "editable": true
        },
        "list": {
          "label": "legacyFeaturedImage",
          "searchable": false,
          "sortable": false
        }
      },
      "legacyMedia": {
        "edit": {
          "label": "legacyMedia",
          "description": "",
          "placeholder": "",
          "visible": true,
          "editable": true
        },
        "list": {
          "label": "legacyMedia",
          "searchable": false,
          "sortable": false
        }
      },
      "link": {
        "edit": {
          "label": "Link",
          "description": "",
          "placeholder": "",
          "visible": true,
          "editable": true
        },
        "list": {
          "label": "Link",
          "searchable": true,
          "sortable": true
        }
      },
      "status": {
        "edit": {
          "label": "Status",
          "description": "",
          "placeholder": "",
          "visible": true,
          "editable": true
        },
        "list": {
          "label": "Status",
          "searchable": true,
          "sortable": true
        }
      },
      "legacyAttributes": {
        "edit": {
          "label": "legacyAttributes",
          "description": "",
          "placeholder": "",
          "visible": true,
          "editable": true
        },
        "list": {
          "label": "legacyAttributes",
          "searchable": false,
          "sortable": false
        }
      },
      "featured": {
        "edit": {
          "label": "featured",
          "description": "",
          "placeholder": "",
          "visible": true,
          "editable": true
        },
        "list": {
          "label": "featured",
          "searchable": true,
          "sortable": true
        }
      },
      "tier": {
        "edit": {
          "label": "tier",
          "description": "",
          "placeholder": "",
          "visible": true,
          "editable": true
        },
        "list": {
          "label": "tier",
          "searchable": true,
          "sortable": true
        }
      },
      "esES": {
        "edit": {
          "label": "esES",
          "description": "",
          "placeholder": "",
          "visible": true,
          "editable": true
        },
        "list": {
          "label": "esES",
          "searchable": true,
          "sortable": true
        }
      },
      "user": {
        "edit": {
          "label": "user",
          "description": "",
          "placeholder": "",
          "visible": true,
          "editable": true,
          "mainField": "username"
        },
        "list": {
          "label": "user",
          "searchable": true,
          "sortable": true
        }
      },
      "template": {
        "edit": {
          "label": "template",
          "description": "",
          "placeholder": "",
          "visible": true,
          "editable": true
        },
        "list": {
          "label": "template",
          "searchable": true,
          "sortable": true
        }
      },
      "createdAt": {
        "edit": {
          "label": "CreatedAt",
          "description": "",
          "placeholder": "",
          "visible": false,
          "editable": true
        },
        "list": {
          "label": "CreatedAt",
          "searchable": true,
          "sortable": true
        }
      },
      "updatedAt": {
        "edit": {
          "label": "UpdatedAt",
          "description": "",
          "placeholder": "",
          "visible": false,
          "editable": true
        },
        "list": {
          "label": "UpdatedAt",
          "searchable": true,
          "sortable": true
        }
      }
    },
    "layouts": {
      "edit": [
        [
          {
            "name": "type",
            "size": 6
          }
        ],
        [
          {
            "name": "legacyId",
            "size": 4
          },
          {
            "name": "date",
            "size": 6
          }
        ],
        [
          {
            "name": "featured",
            "size": 4
          },
          {
            "name": "tier",
            "size": 4
          }
        ],
        [
          {
            "name": "excerpt",
            "size": 6
          },
          {
            "name": "slug",
            "size": 6
          }
        ],
        [
          {
            "name": "title",
            "size": 6
          }
        ],
        [
          {
            "name": "content",
            "size": 12
          }
        ],
        [
          {
            "name": "featuredImage",
            "size": 6
          }
        ],
        [
          {
            "name": "link",
            "size": 6
          },
          {
            "name": "status",
            "size": 6
          }
        ],
        [
          {
            "name": "seo",
            "size": 12
          }
        ],
        [
          {
            "name": "legacyFeaturedImage",
            "size": 12
          }
        ],
        [
          {
            "name": "legacyMedia",
            "size": 12
          }
        ],
        [
          {
            "name": "legacyAttributes",
            "size": 12
          }
        ],
        [
          {
            "name": "esES",
            "size": 4
          },
          {
            "name": "template",
            "size": 4
          }
        ],
        [
          {
            "name": "gallery",
            "size": 6
          }
        ]
      ],
      "editRelations": [
        "tags",
        "user"
      ],
      "list": [
        "id",
        "date",
        "legacyId",
        "title"
      ]
    }
  },
  "type": "object",
  "environment": null,
  "tag": null
}